Metadata-Version: 2.1
Name: ipy2neo
Version: 1.0.0
Summary: Interactive Neo4j console built on py2neo
Home-page: https://py2neo.org/ipy2neo
Author: Nigel Small
Author-email: technige@py2neo.org
License: Apache License, Version 2.0
Project-URL: Bug Tracker, https://github.com/py2neo-org/ipy2neo/issues
Project-URL: Documentation, https://py2neo.org/ipy2neo/
Project-URL: Source Code, https://github.com/py2neo-org/ipy2neo
Platform: UNKNOWN
Classifier: Development Status :: 6 - Mature
Classifier: Environment :: Console
Classifier: Intended Audience :: Developers
Classifier: Intended Audience :: Information Technology
Classifier: Intended Audience :: Science/Research
Classifier: License :: OSI Approved :: Apache Software License
Classifier: Natural Language :: English
Classifier: Operating System :: OS Independent
Classifier: Programming Language :: Python
Classifier: Programming Language :: Python :: 2
Classifier: Programming Language :: Python :: 2.7
Classifier: Programming Language :: Python :: 3
Classifier: Programming Language :: Python :: 3.5
Classifier: Programming Language :: Python :: 3.6
Classifier: Programming Language :: Python :: 3.7
Classifier: Programming Language :: Python :: 3.8
Classifier: Programming Language :: Python :: 3.9
Classifier: Programming Language :: Python :: Implementation :: CPython
Classifier: Topic :: Database
Classifier: Topic :: Database :: Database Engines/Servers
Classifier: Topic :: Scientific/Engineering
Classifier: Topic :: Software Development
Classifier: Topic :: Software Development :: Libraries
